{
    "config": {},
    "instance_base": {
        "config": {},
        "groups": [],
        "instances": [
            {
                "bindTo": [
                    "特色小镇概念/小镇管理委员会"
                ],
                "config": {},
                "data_properties": {},
                "graph_data": {},
                "id": "2021/4/19 下午5:44:251031",
                "name": "管委会A@2",
                "object_properties": [],
                "type": [
                    "特色小镇概念/Participant"
                ]
            },
            {
                "bindTo": [
                    "特色小镇概念/小镇管理委员会"
                ],
                "config": {},
                "data_properties": {},
                "graph_data": {},
                "id": "2021/4/19 下午5:44:251031",
                "name": "管委会A@3",
                "object_properties": [],
                "type": [
                    "特色小镇概念/Participant"
                ]
            },
            {
                "bindTo": [
                    "特色小镇概念/小镇管理委员会"
                ],
                "config": {},
                "data_properties": {},
                "graph_data": {},
                "id": "2021/4/19 下午5:44:251031",
                "name": "管委会A@4",
                "object_properties": [],
                "type": [
                    "特色小镇概念/Participant"
                ]
            },
            {
                "bindTo": [
                    "特色小镇概念/企业"
                ],
                "config": {},
                "data_properties": {},
                "graph_data": {},
                "id": "2021/4/19 下午5:45:021032",
                "name": "企业A@0",
                "object_properties": [],
                "type": [
                    "特色小镇概念/Participant"
                ]
            },
            {
                "bindTo": [
                    "特色小镇概念/企业"
                ],
                "config": {},
                "data_properties": {},
                "graph_data": {},
                "id": "2021/4/19 下午5:45:021032",
                "name": "企业A@3",
                "object_properties": [],
                "type": [
                    "特色小镇概念/Participant"
                ]
            },
            {
                "bindTo": [
                    "特色小镇概念/24小时自助办税服务厅"
                ],
                "config": {},
                "data_properties": {},
                "graph_data": {},
                "id": "2021/4/19 下午5:45:241033",
                "name": "办税厅A@2",
                "object_properties": [],
                "type": [
                    "特色小镇概念/Participant"
                ]
            },
            {
                "bindTo": [
                    "特色小镇概念/24小时自助办税服务厅"
                ],
                "config": {},
                "data_properties": {},
                "graph_data": {},
                "id": "2021/4/19 下午5:45:241033",
                "name": "办税厅A@3",
                "object_properties": [],
                "type": [
                    "特色小镇概念/Participant"
                ]
            },
            {
                "bindTo": [
                    "特色小镇概念/24小时自助办税服务厅"
                ],
                "config": {},
                "data_properties": {},
                "graph_data": {},
                "id": "2021/4/19 下午5:45:241033",
                "name": "办税厅A@1",
                "object_properties": [],
                "type": [
                    "特色小镇概念/Participant"
                ]
            },
            {
                "bindTo": [
                    "特色小镇概念/企业"
                ],
                "config": {},
                "data_properties": {},
                "graph_data": {},
                "id": "2021/4/19 下午5:45:021032",
                "name": "企业A@4",
                "object_properties": [],
                "type": [
                    "特色小镇概念/Participant"
                ]
            },
            {
                "bindTo": [
                    "特色小镇概念/小镇管理委员会"
                ],
                "config": {},
                "data_properties": {},
                "graph_data": {},
                "id": "2021/4/19 下午5:44:251031",
                "name": "管委会A@1",
                "object_properties": [],
                "type": [
                    "特色小镇概念/Participant"
                ]
            },
            {
                "bindTo": [
                    "特色小镇概念/企业"
                ],
                "config": {},
                "data_properties": {},
                "graph_data": {},
                "id": "2021/4/19 下午5:45:021032",
                "name": "企业A@1",
                "object_properties": [],
                "type": [
                    "特色小镇概念/Participant"
                ]
            },
            {
                "bindTo": [],
                "config": {},
                "data_properties": {
                    "基础领域术语库/amount": {
                        "isPattern": false,
                        "text": "740",
                        "type": "value"
                    },
                    "基础领域术语库/quota_dscp": {
                        "isPattern": false,
                        "text": "6.0",
                        "type": "value"
                    }
                },
                "graph_data": {},
                "id": "2021/4/19 下午5:46:411035",
                "name": "Process平均运行时间",
                "object_properties": [],
                "type": [
                    "基础领域术语库/Quota"
                ]
            },
            {
                "bindTo": [
                    "特色小镇概念/24小时自助办税服务厅"
                ],
                "config": {},
                "data_properties": {},
                "graph_data": {},
                "id": "2021/4/19 下午5:45:241033",
                "name": "办税厅A@0",
                "object_properties": [],
                "type": [
                    "特色小镇概念/Participant"
                ]
            },
            {
                "bindTo": [
                    "特色小镇概念/小镇管理委员会"
                ],
                "config": {},
                "data_properties": {},
                "graph_data": {},
                "id": "2021/4/19 下午5:44:251031",
                "name": "管委会A@0",
                "object_properties": [],
                "type": [
                    "特色小镇概念/Participant"
                ]
            },
            {
                "bindTo": [
                    "特色小镇概念/企业"
                ],
                "config": {},
                "data_properties": {},
                "graph_data": {},
                "id": "2021/4/19 下午5:45:021032",
                "name": "企业A@2",
                "object_properties": [],
                "type": [
                    "特色小镇概念/Participant"
                ]
            },
            {
                "bindTo": [
                    "特色小镇概念/24小时自助办税服务厅"
                ],
                "config": {},
                "data_properties": {},
                "graph_data": {},
                "id": "2021/4/19 下午5:45:241033",
                "name": "办税厅A@4",
                "object_properties": [],
                "type": [
                    "特色小镇概念/Participant"
                ]
            }
        ],
        "relations": []
    },
    "process": [
        {
            "role": {
                "特色小镇概念/24小时自助办税服务厅": "办税厅A@0",
                "特色小镇概念/企业": "企业A@3",
                "特色小镇概念/小镇管理委员会": "管委会A@3"
            },
            "tokens": [
                {
                    "BPMN_node": "纳税成功",
                    "data": {
                        "start_step": 150
                    },
                    "has_gen_next": false,
                    "id": "1618825432.1269433_28264200",
                    "is_executed": false,
                    "is_fail": false,
                    "now_duration": 1
                }
            ]
        },
        {
            "role": {
                "特色小镇概念/24小时自助办税服务厅": "办税厅A@1",
                "特色小镇概念/企业": "企业A@4",
                "特色小镇概念/小镇管理委员会": "管委会A@0"
            },
            "tokens": [
                {
                    "BPMN_node": "纳税成功",
                    "data": {
                        "start_step": 150
                    },
                    "has_gen_next": false,
                    "id": "1618825432.127278_28264203",
                    "is_executed": false,
                    "is_fail": false,
                    "now_duration": 1
                }
            ]
        },
        {
            "role": {
                "特色小镇概念/24小时自助办税服务厅": "办税厅A@1",
                "特色小镇概念/企业": "企业A@3",
                "特色小镇概念/小镇管理委员会": "管委会A@0"
            },
            "tokens": [
                {
                    "BPMN_node": "纳税身份核实",
                    "data": {
                        "start_step": 152
                    },
                    "has_gen_next": false,
                    "id": "1618825432.1260884_28264193",
                    "is_executed": false,
                    "is_fail": false,
                    "now_duration": 1
                }
            ]
        },
        {
            "role": {
                "特色小镇概念/24小时自助办税服务厅": "办税厅A@2",
                "特色小镇概念/企业": "企业A@3",
                "特色小镇概念/小镇管理委员会": "管委会A@0"
            },
            "tokens": [
                {
                    "BPMN_node": "BPMN概念/EndEvent-1",
                    "data": {
                        "start_step": 149
                    },
                    "has_gen_next": false,
                    "id": "1618825432.1270232_28264201",
                    "is_executed": false,
                    "is_fail": false,
                    "now_duration": 1
                }
            ]
        },
        {
            "role": {
                "特色小镇概念/24小时自助办税服务厅": "办税厅A@1",
                "特色小镇概念/企业": "企业A@1",
                "特色小镇概念/小镇管理委员会": "管委会A@2"
            },
            "tokens": [
                {
                    "BPMN_node": "企业注册",
                    "data": {
                        "start_step": 154
                    },
                    "has_gen_next": false,
                    "id": "1618825432.1242204_28264182",
                    "is_executed": false,
                    "is_fail": false,
                    "now_duration": 1
                }
            ]
        },
        {
            "role": {
                "特色小镇概念/24小时自助办税服务厅": "办税厅A@2",
                "特色小镇概念/企业": "企业A@0",
                "特色小镇概念/小镇管理委员会": "管委会A@1"
            },
            "tokens": [
                {
                    "BPMN_node": "纳税成功",
                    "data": {
                        "start_step": 150
                    },
                    "has_gen_next": false,
                    "id": "1618825432.127095_28264202",
                    "is_executed": false,
                    "is_fail": false,
                    "now_duration": 1
                }
            ]
        },
        {
            "role": {
                "特色小镇概念/24小时自助办税服务厅": "办税厅A@2",
                "特色小镇概念/企业": "企业A@1",
                "特色小镇概念/小镇管理委员会": "管委会A@3"
            },
            "tokens": [
                {
                    "BPMN_node": "纳税身份核实",
                    "data": {
                        "start_step": 152
                    },
                    "has_gen_next": false,
                    "id": "1618825432.1246223_28264185",
                    "is_executed": false,
                    "is_fail": false,
                    "now_duration": 1
                }
            ]
        },
        {
            "role": {
                "特色小镇概念/24小时自助办税服务厅": "办税厅A@2",
                "特色小镇概念/企业": "企业A@4",
                "特色小镇概念/小镇管理委员会": "管委会A@1"
            },
            "tokens": [
                {
                    "BPMN_node": "办税厅出入口人脸识别",
                    "data": {
                        "start_step": 153
                    },
                    "has_gen_next": false,
                    "id": "1618825432.123957_28264181",
                    "is_executed": false,
                    "is_fail": false,
                    "now_duration": 1
                }
            ]
        },
        {
            "role": {
                "特色小镇概念/24小时自助办税服务厅": "办税厅A@0",
                "特色小镇概念/企业": "企业A@4",
                "特色小镇概念/小镇管理委员会": "管委会A@2"
            },
            "tokens": [
                {
                    "BPMN_node": "BPMN概念/EndEvent-1",
                    "data": {
                        "start_step": 149
                    },
                    "has_gen_next": false,
                    "id": "1618825432.1267912_28264198",
                    "is_executed": false,
                    "is_fail": false,
                    "now_duration": 1
                }
            ]
        },
        {
            "role": {
                "特色小镇概念/24小时自助办税服务厅": "办税厅A@2",
                "特色小镇概念/企业": "企业A@4",
                "特色小镇概念/小镇管理委员会": "管委会A@2"
            },
            "tokens": [
                {
                    "BPMN_node": "税收征缴",
                    "data": {
                        "start_step": 151
                    },
                    "has_gen_next": false,
                    "id": "1618825432.12639_28264195",
                    "is_executed": false,
                    "is_fail": false,
                    "now_duration": 1
                }
            ]
        },
        {
            "role": {
                "特色小镇概念/24小时自助办税服务厅": "办税厅A@0",
                "特色小镇概念/企业": "企业A@2",
                "特色小镇概念/小镇管理委员会": "管委会A@0"
            },
            "tokens": [
                {
                    "BPMN_node": "纳税成功",
                    "data": {
                        "start_step": 150
                    },
                    "has_gen_next": false,
                    "id": "1618825432.125516_28264190",
                    "is_executed": false,
                    "is_fail": false,
                    "now_duration": 1
                }
            ]
        },
        {
            "role": {
                "特色小镇概念/24小时自助办税服务厅": "办税厅A@0",
                "特色小镇概念/企业": "企业A@2",
                "特色小镇概念/小镇管理委员会": "管委会A@2"
            },
            "tokens": [
                {
                    "BPMN_node": "税收征缴",
                    "data": {
                        "start_step": 151
                    },
                    "has_gen_next": false,
                    "id": "1618825432.1234655_28264180",
                    "is_executed": false,
                    "is_fail": false,
                    "now_duration": 1
                }
            ]
        },
        {
            "role": {
                "特色小镇概念/24小时自助办税服务厅": "办税厅A@2",
                "特色小镇概念/企业": "企业A@2",
                "特色小镇概念/小镇管理委员会": "管委会A@3"
            },
            "tokens": [
                {
                    "BPMN_node": "纳税身份核实",
                    "data": {
                        "start_step": 152
                    },
                    "has_gen_next": false,
                    "id": "1618825432.127359_28264204",
                    "is_executed": false,
                    "is_fail": false,
                    "now_duration": 1
                }
            ]
        },
        {
            "role": {
                "特色小镇概念/24小时自助办税服务厅": "办税厅A@4",
                "特色小镇概念/企业": "企业A@3",
                "特色小镇概念/小镇管理委员会": "管委会A@2"
            },
            "tokens": [
                {
                    "BPMN_node": "企业注册",
                    "data": {
                        "start_step": 154
                    },
                    "has_gen_next": false,
                    "id": "1618825432.1268659_28264199",
                    "is_executed": false,
                    "is_fail": false,
                    "now_duration": 1
                }
            ]
        },
        {
            "role": {
                "特色小镇概念/24小时自助办税服务厅": "办税厅A@4",
                "特色小镇概念/企业": "企业A@2",
                "特色小镇概念/小镇管理委员会": "管委会A@1"
            },
            "tokens": [
                {
                    "BPMN_node": "企业注册",
                    "data": {
                        "start_step": 154
                    },
                    "has_gen_next": false,
                    "id": "1618825432.1232915_28264178",
                    "is_executed": false,
                    "is_fail": false,
                    "now_duration": 1
                }
            ]
        },
        {
            "role": {
                "特色小镇概念/24小时自助办税服务厅": "办税厅A@0",
                "特色小镇概念/企业": "企业A@4",
                "特色小镇概念/小镇管理委员会": "管委会A@0"
            },
            "tokens": [
                {
                    "BPMN_node": "企业注册",
                    "data": {
                        "start_step": 154
                    },
                    "has_gen_next": false,
                    "id": "1618825432.1280386_28264206",
                    "is_executed": false,
                    "is_fail": false,
                    "now_duration": 1
                }
            ]
        },
        {
            "role": {
                "特色小镇概念/24小时自助办税服务厅": "办税厅A@3",
                "特色小镇概念/企业": "企业A@1",
                "特色小镇概念/小镇管理委员会": "管委会A@2"
            },
            "tokens": [
                {
                    "BPMN_node": "BPMN概念/EndEvent-1",
                    "data": {
                        "start_step": 149
                    },
                    "has_gen_next": false,
                    "id": "1618825432.1249828_28264187",
                    "is_executed": false,
                    "is_fail": false,
                    "now_duration": 1
                }
            ]
        },
        {
            "role": {
                "特色小镇概念/24小时自助办税服务厅": "办税厅A@2",
                "特色小镇概念/企业": "企业A@2",
                "特色小镇概念/小镇管理委员会": "管委会A@1"
            },
            "tokens": [
                {
                    "BPMN_node": "办税厅出入口人脸识别",
                    "data": {
                        "start_step": 153
                    },
                    "has_gen_next": false,
                    "id": "1618825432.1243236_28264183",
                    "is_executed": false,
                    "is_fail": false,
                    "now_duration": 1
                }
            ]
        },
        {
            "role": {
                "特色小镇概念/24小时自助办税服务厅": "办税厅A@0",
                "特色小镇概念/企业": "企业A@0",
                "特色小镇概念/小镇管理委员会": "管委会A@1"
            },
            "tokens": [
                {
                    "BPMN_node": "BPMN概念/EndEvent-1",
                    "data": {
                        "start_step": 149
                    },
                    "has_gen_next": false,
                    "id": "1618825432.1254332_28264189",
                    "is_executed": false,
                    "is_fail": false,
                    "now_duration": 1
                }
            ]
        },
        {
            "role": {
                "特色小镇概念/24小时自助办税服务厅": "办税厅A@3",
                "特色小镇概念/企业": "企业A@3",
                "特色小镇概念/小镇管理委员会": "管委会A@4"
            },
            "tokens": [
                {
                    "BPMN_node": "税收征缴",
                    "data": {
                        "start_step": 151
                    },
                    "has_gen_next": false,
                    "id": "1618825432.1252558_28264188",
                    "is_executed": false,
                    "is_fail": false,
                    "now_duration": 1
                }
            ]
        },
        {
            "role": {
                "特色小镇概念/24小时自助办税服务厅": "办税厅A@3",
                "特色小镇概念/企业": "企业A@4",
                "特色小镇概念/小镇管理委员会": "管委会A@0"
            },
            "tokens": [
                {
                    "BPMN_node": "纳税身份核实",
                    "data": {
                        "start_step": 152
                    },
                    "has_gen_next": false,
                    "id": "1618825432.1258667_28264192",
                    "is_executed": false,
                    "is_fail": false,
                    "now_duration": 1
                }
            ]
        },
        {
            "role": {
                "特色小镇概念/24小时自助办税服务厅": "办税厅A@4",
                "特色小镇概念/企业": "企业A@2",
                "特色小镇概念/小镇管理委员会": "管委会A@4"
            },
            "tokens": [
                {
                    "BPMN_node": "BPMN概念/EndEvent-1",
                    "data": {
                        "start_step": 149
                    },
                    "has_gen_next": false,
                    "id": "1618825432.126629_28264196",
                    "is_executed": false,
                    "is_fail": false,
                    "now_duration": 1
                }
            ]
        },
        {
            "role": {
                "特色小镇概念/24小时自助办税服务厅": "办税厅A@4",
                "特色小镇概念/企业": "企业A@1",
                "特色小镇概念/小镇管理委员会": "管委会A@0"
            },
            "tokens": [
                {
                    "BPMN_node": "办税厅出入口人脸识别",
                    "data": {
                        "start_step": 153
                    },
                    "has_gen_next": false,
                    "id": "1618825432.125783_28264191",
                    "is_executed": false,
                    "is_fail": false,
                    "now_duration": 1
                }
            ]
        },
        {
            "role": {
                "特色小镇概念/24小时自助办税服务厅": "办税厅A@3",
                "特色小镇概念/企业": "企业A@1",
                "特色小镇概念/小镇管理委员会": "管委会A@4"
            },
            "tokens": [
                {
                    "BPMN_node": "税收征缴",
                    "data": {
                        "start_step": 151
                    },
                    "has_gen_next": false,
                    "id": "1618825432.1281261_28264207",
                    "is_executed": false,
                    "is_fail": false,
                    "now_duration": 1
                }
            ]
        },
        {
            "role": {
                "特色小镇概念/24小时自助办税服务厅": "办税厅A@4",
                "特色小镇概念/企业": "企业A@0",
                "特色小镇概念/小镇管理委员会": "管委会A@2"
            },
            "tokens": [
                {
                    "BPMN_node": "企业注册",
                    "data": {
                        "start_step": 154
                    },
                    "has_gen_next": false,
                    "id": "1618825432.1263053_28264194",
                    "is_executed": false,
                    "is_fail": false,
                    "now_duration": 1
                }
            ]
        },
        {
            "role": {
                "特色小镇概念/24小时自助办税服务厅": "办税厅A@4",
                "特色小镇概念/企业": "企业A@1",
                "特色小镇概念/小镇管理委员会": "管委会A@3"
            },
            "tokens": [
                {
                    "BPMN_node": "纳税成功",
                    "data": {
                        "start_step": 150
                    },
                    "has_gen_next": false,
                    "id": "1618825432.123383_28264179",
                    "is_executed": false,
                    "is_fail": false,
                    "now_duration": 1
                }
            ]
        },
        {
            "role": {
                "特色小镇概念/24小时自助办税服务厅": "办税厅A@4",
                "特色小镇概念/企业": "企业A@0",
                "特色小镇概念/小镇管理委员会": "管委会A@0"
            },
            "tokens": [
                {
                    "BPMN_node": "税收征缴",
                    "data": {
                        "start_step": 151
                    },
                    "has_gen_next": false,
                    "id": "1618825432.1277823_28264205",
                    "is_executed": false,
                    "is_fail": false,
                    "now_duration": 1
                }
            ]
        },
        {
            "role": {
                "特色小镇概念/24小时自助办税服务厅": "办税厅A@1",
                "特色小镇概念/企业": "企业A@0",
                "特色小镇概念/小镇管理委员会": "管委会A@2"
            },
            "tokens": [
                {
                    "BPMN_node": "纳税身份核实",
                    "data": {
                        "start_step": 152
                    },
                    "has_gen_next": false,
                    "id": "1618825432.1244087_28264184",
                    "is_executed": false,
                    "is_fail": false,
                    "now_duration": 1
                }
            ]
        },
        {
            "role": {
                "特色小镇概念/24小时自助办税服务厅": "办税厅A@4",
                "特色小镇概念/企业": "企业A@3",
                "特色小镇概念/小镇管理委员会": "管委会A@2"
            },
            "tokens": [
                {
                    "BPMN_node": "办税厅出入口人脸识别",
                    "data": {
                        "start_step": 153
                    },
                    "has_gen_next": false,
                    "id": "1618825432.12671_28264197",
                    "is_executed": false,
                    "is_fail": false,
                    "now_duration": 1
                }
            ]
        },
        {
            "role": {
                "特色小镇概念/24小时自助办税服务厅": "办税厅A@4",
                "特色小镇概念/企业": "企业A@0",
                "特色小镇概念/小镇管理委员会": "管委会A@2"
            },
            "tokens": [
                {
                    "BPMN_node": "办税厅出入口人脸识别",
                    "data": {
                        "start_step": 153
                    },
                    "has_gen_next": false,
                    "id": "1618825432.124893_28264186",
                    "is_executed": false,
                    "is_fail": false,
                    "now_duration": 1
                }
            ]
        }
    ],
    "quota": {
        "Process平均运行时间": {
            "name": "Process平均运行时间",
            "text": "0",
            "type": "value",
            "val": 6.0
        }
    },
    "step_count": 154
}