{
    "config": {},
    "instance_base": {
        "config": {},
        "groups": [],
        "instances": [
            {
                "bindTo": [
                    "特色小镇概念/小镇管理委员会"
                ],
                "config": {},
                "data_properties": {},
                "graph_data": {},
                "id": "2021/4/19 下午5:44:251031",
                "name": "管委会A@0",
                "object_properties": [],
                "type": [
                    "特色小镇概念/Participant"
                ]
            },
            {
                "bindTo": [
                    "特色小镇概念/企业"
                ],
                "config": {},
                "data_properties": {},
                "graph_data": {},
                "id": "2021/4/19 下午5:45:021032",
                "name": "企业A@0",
                "object_properties": [],
                "type": [
                    "特色小镇概念/Participant"
                ]
            },
            {
                "bindTo": [
                    "特色小镇概念/24小时自助办税服务厅"
                ],
                "config": {},
                "data_properties": {},
                "graph_data": {},
                "id": "2021/4/19 下午5:45:241033",
                "name": "办税厅A@3",
                "object_properties": [],
                "type": [
                    "特色小镇概念/Participant"
                ]
            },
            {
                "bindTo": [
                    "特色小镇概念/24小时自助办税服务厅"
                ],
                "config": {},
                "data_properties": {},
                "graph_data": {},
                "id": "2021/4/19 下午5:45:241033",
                "name": "办税厅A@2",
                "object_properties": [],
                "type": [
                    "特色小镇概念/Participant"
                ]
            },
            {
                "bindTo": [
                    "特色小镇概念/24小时自助办税服务厅"
                ],
                "config": {},
                "data_properties": {},
                "graph_data": {},
                "id": "2021/4/19 下午5:45:241033",
                "name": "办税厅A@4",
                "object_properties": [],
                "type": [
                    "特色小镇概念/Participant"
                ]
            },
            {
                "bindTo": [
                    "特色小镇概念/企业"
                ],
                "config": {},
                "data_properties": {},
                "graph_data": {},
                "id": "2021/4/19 下午5:45:021032",
                "name": "企业A@4",
                "object_properties": [],
                "type": [
                    "特色小镇概念/Participant"
                ]
            },
            {
                "bindTo": [
                    "特色小镇概念/小镇管理委员会"
                ],
                "config": {},
                "data_properties": {},
                "graph_data": {},
                "id": "2021/4/19 下午5:44:251031",
                "name": "管委会A@4",
                "object_properties": [],
                "type": [
                    "特色小镇概念/Participant"
                ]
            },
            {
                "bindTo": [],
                "config": {},
                "data_properties": {
                    "基础领域术语库/amount": {
                        "isPattern": false,
                        "text": "670",
                        "type": "value"
                    },
                    "基础领域术语库/quota_dscp": {
                        "isPattern": false,
                        "text": "6.0",
                        "type": "value"
                    }
                },
                "graph_data": {},
                "id": "2021/4/19 下午5:46:411035",
                "name": "Process平均运行时间",
                "object_properties": [],
                "type": [
                    "基础领域术语库/Quota"
                ]
            },
            {
                "bindTo": [
                    "特色小镇概念/企业"
                ],
                "config": {},
                "data_properties": {},
                "graph_data": {},
                "id": "2021/4/19 下午5:45:021032",
                "name": "企业A@3",
                "object_properties": [],
                "type": [
                    "特色小镇概念/Participant"
                ]
            },
            {
                "bindTo": [
                    "特色小镇概念/小镇管理委员会"
                ],
                "config": {},
                "data_properties": {},
                "graph_data": {},
                "id": "2021/4/19 下午5:44:251031",
                "name": "管委会A@2",
                "object_properties": [],
                "type": [
                    "特色小镇概念/Participant"
                ]
            },
            {
                "bindTo": [
                    "特色小镇概念/企业"
                ],
                "config": {},
                "data_properties": {},
                "graph_data": {},
                "id": "2021/4/19 下午5:45:021032",
                "name": "企业A@1",
                "object_properties": [],
                "type": [
                    "特色小镇概念/Participant"
                ]
            },
            {
                "bindTo": [
                    "特色小镇概念/小镇管理委员会"
                ],
                "config": {},
                "data_properties": {},
                "graph_data": {},
                "id": "2021/4/19 下午5:44:251031",
                "name": "管委会A@3",
                "object_properties": [],
                "type": [
                    "特色小镇概念/Participant"
                ]
            },
            {
                "bindTo": [
                    "特色小镇概念/24小时自助办税服务厅"
                ],
                "config": {},
                "data_properties": {},
                "graph_data": {},
                "id": "2021/4/19 下午5:45:241033",
                "name": "办税厅A@0",
                "object_properties": [],
                "type": [
                    "特色小镇概念/Participant"
                ]
            },
            {
                "bindTo": [
                    "特色小镇概念/24小时自助办税服务厅"
                ],
                "config": {},
                "data_properties": {},
                "graph_data": {},
                "id": "2021/4/19 下午5:45:241033",
                "name": "办税厅A@1",
                "object_properties": [],
                "type": [
                    "特色小镇概念/Participant"
                ]
            },
            {
                "bindTo": [
                    "特色小镇概念/小镇管理委员会"
                ],
                "config": {},
                "data_properties": {},
                "graph_data": {},
                "id": "2021/4/19 下午5:44:251031",
                "name": "管委会A@1",
                "object_properties": [],
                "type": [
                    "特色小镇概念/Participant"
                ]
            },
            {
                "bindTo": [
                    "特色小镇概念/企业"
                ],
                "config": {},
                "data_properties": {},
                "graph_data": {},
                "id": "2021/4/19 下午5:45:021032",
                "name": "企业A@2",
                "object_properties": [],
                "type": [
                    "特色小镇概念/Participant"
                ]
            }
        ],
        "relations": []
    },
    "process": [
        {
            "role": {
                "特色小镇概念/24小时自助办税服务厅": "办税厅A@4",
                "特色小镇概念/企业": "企业A@4",
                "特色小镇概念/小镇管理委员会": "管委会A@2"
            },
            "tokens": [
                {
                    "BPMN_node": "BPMN概念/EndEvent-1",
                    "data": {
                        "start_step": 135
                    },
                    "has_gen_next": false,
                    "id": "1618825448.347883_28286582",
                    "is_executed": false,
                    "is_fail": false,
                    "now_duration": 1
                }
            ]
        },
        {
            "role": {
                "特色小镇概念/24小时自助办税服务厅": "办税厅A@3",
                "特色小镇概念/企业": "企业A@0",
                "特色小镇概念/小镇管理委员会": "管委会A@0"
            },
            "tokens": [
                {
                    "BPMN_node": "税收征缴",
                    "data": {
                        "start_step": 137
                    },
                    "has_gen_next": false,
                    "id": "1618825448.348357_28286586",
                    "is_executed": false,
                    "is_fail": false,
                    "now_duration": 1
                }
            ]
        },
        {
            "role": {
                "特色小镇概念/24小时自助办税服务厅": "办税厅A@3",
                "特色小镇概念/企业": "企业A@1",
                "特色小镇概念/小镇管理委员会": "管委会A@4"
            },
            "tokens": [
                {
                    "BPMN_node": "纳税成功",
                    "data": {
                        "start_step": 136
                    },
                    "has_gen_next": false,
                    "id": "1618825448.349217_28286590",
                    "is_executed": false,
                    "is_fail": false,
                    "now_duration": 1
                }
            ]
        },
        {
            "role": {
                "特色小镇概念/24小时自助办税服务厅": "办税厅A@3",
                "特色小镇概念/企业": "企业A@0",
                "特色小镇概念/小镇管理委员会": "管委会A@2"
            },
            "tokens": [
                {
                    "BPMN_node": "企业注册",
                    "data": {
                        "start_step": 140
                    },
                    "has_gen_next": false,
                    "id": "1618825448.3482492_28286585",
                    "is_executed": false,
                    "is_fail": false,
                    "now_duration": 1
                }
            ]
        },
        {
            "role": {
                "特色小镇概念/24小时自助办税服务厅": "办税厅A@0",
                "特色小镇概念/企业": "企业A@2",
                "特色小镇概念/小镇管理委员会": "管委会A@0"
            },
            "tokens": [
                {
                    "BPMN_node": "税收征缴",
                    "data": {
                        "start_step": 137
                    },
                    "has_gen_next": false,
                    "id": "1618825448.3499703_28286596",
                    "is_executed": false,
                    "is_fail": false,
                    "now_duration": 1
                }
            ]
        },
        {
            "role": {
                "特色小镇概念/24小时自助办税服务厅": "办税厅A@3",
                "特色小镇概念/企业": "企业A@0",
                "特色小镇概念/小镇管理委员会": "管委会A@0"
            },
            "tokens": [
                {
                    "BPMN_node": "办税厅出入口人脸识别",
                    "data": {
                        "start_step": 139
                    },
                    "has_gen_next": false,
                    "id": "1618825448.3507102_28286600",
                    "is_executed": false,
                    "is_fail": false,
                    "now_duration": 1
                }
            ]
        },
        {
            "role": {
                "特色小镇概念/24小时自助办税服务厅": "办税厅A@2",
                "特色小镇概念/企业": "企业A@0",
                "特色小镇概念/小镇管理委员会": "管委会A@0"
            },
            "tokens": [
                {
                    "BPMN_node": "纳税身份核实",
                    "data": {
                        "start_step": 138
                    },
                    "has_gen_next": false,
                    "id": "1618825448.3490226_28286589",
                    "is_executed": false,
                    "is_fail": false,
                    "now_duration": 1
                }
            ]
        },
        {
            "role": {
                "特色小镇概念/24小时自助办税服务厅": "办税厅A@4",
                "特色小镇概念/企业": "企业A@3",
                "特色小镇概念/小镇管理委员会": "管委会A@4"
            },
            "tokens": [
                {
                    "BPMN_node": "办税厅出入口人脸识别",
                    "data": {
                        "start_step": 139
                    },
                    "has_gen_next": false,
                    "id": "1618825448.3497262_28286594",
                    "is_executed": false,
                    "is_fail": false,
                    "now_duration": 1
                }
            ]
        },
        {
            "role": {
                "特色小镇概念/24小时自助办税服务厅": "办税厅A@2",
                "特色小镇概念/企业": "企业A@3",
                "特色小镇概念/小镇管理委员会": "管委会A@3"
            },
            "tokens": [
                {
                    "BPMN_node": "纳税成功",
                    "data": {
                        "start_step": 136
                    },
                    "has_gen_next": false,
                    "id": "1618825448.3487253_28286587",
                    "is_executed": false,
                    "is_fail": false,
                    "now_duration": 1
                }
            ]
        },
        {
            "role": {
                "特色小镇概念/24小时自助办税服务厅": "办税厅A@0",
                "特色小镇概念/企业": "企业A@3",
                "特色小镇概念/小镇管理委员会": "管委会A@1"
            },
            "tokens": [
                {
                    "BPMN_node": "BPMN概念/EndEvent-1",
                    "data": {
                        "start_step": 135
                    },
                    "has_gen_next": false,
                    "id": "1618825448.350788_28286601",
                    "is_executed": false,
                    "is_fail": false,
                    "now_duration": 1
                }
            ]
        },
        {
            "role": {
                "特色小镇概念/24小时自助办税服务厅": "办税厅A@1",
                "特色小镇概念/企业": "企业A@2",
                "特色小镇概念/小镇管理委员会": "管委会A@0"
            },
            "tokens": [
                {
                    "BPMN_node": "纳税成功",
                    "data": {
                        "start_step": 136
                    },
                    "has_gen_next": false,
                    "id": "1618825448.3470883_28286577",
                    "is_executed": false,
                    "is_fail": false,
                    "now_duration": 1
                }
            ]
        },
        {
            "role": {
                "特色小镇概念/24小时自助办税服务厅": "办税厅A@3",
                "特色小镇概念/企业": "企业A@4",
                "特色小镇概念/小镇管理委员会": "管委会A@1"
            },
            "tokens": [
                {
                    "BPMN_node": "办税厅出入口人脸识别",
                    "data": {
                        "start_step": 139
                    },
                    "has_gen_next": false,
                    "id": "1618825448.3506315_28286599",
                    "is_executed": false,
                    "is_fail": false,
                    "now_duration": 1
                }
            ]
        },
        {
            "role": {
                "特色小镇概念/24小时自助办税服务厅": "办税厅A@2",
                "特色小镇概念/企业": "企业A@4",
                "特色小镇概念/小镇管理委员会": "管委会A@3"
            },
            "tokens": [
                {
                    "BPMN_node": "纳税身份核实",
                    "data": {
                        "start_step": 138
                    },
                    "has_gen_next": false,
                    "id": "1618825448.3476954_28286581",
                    "is_executed": false,
                    "is_fail": false,
                    "now_duration": 1
                }
            ]
        },
        {
            "role": {
                "特色小镇概念/24小时自助办税服务厅": "办税厅A@3",
                "特色小镇概念/企业": "企业A@4",
                "特色小镇概念/小镇管理委员会": "管委会A@1"
            },
            "tokens": [
                {
                    "BPMN_node": "纳税成功",
                    "data": {
                        "start_step": 136
                    },
                    "has_gen_next": false,
                    "id": "1618825448.3470125_28286576",
                    "is_executed": false,
                    "is_fail": false,
                    "now_duration": 1
                }
            ]
        },
        {
            "role": {
                "特色小镇概念/24小时自助办税服务厅": "办税厅A@0",
                "特色小镇概念/企业": "企业A@0",
                "特色小镇概念/小镇管理委员会": "管委会A@3"
            },
            "tokens": [
                {
                    "BPMN_node": "BPMN概念/EndEvent-1",
                    "data": {
                        "start_step": 135
                    },
                    "has_gen_next": false,
                    "id": "1618825448.348168_28286584",
                    "is_executed": false,
                    "is_fail": false,
                    "now_duration": 1
                }
            ]
        },
        {
            "role": {
                "特色小镇概念/24小时自助办税服务厅": "办税厅A@3",
                "特色小镇概念/企业": "企业A@1",
                "特色小镇概念/小镇管理委员会": "管委会A@0"
            },
            "tokens": [
                {
                    "BPMN_node": "企业注册",
                    "data": {
                        "start_step": 140
                    },
                    "has_gen_next": false,
                    "id": "1618825448.3496437_28286593",
                    "is_executed": false,
                    "is_fail": false,
                    "now_duration": 1
                }
            ]
        },
        {
            "role": {
                "特色小镇概念/24小时自助办税服务厅": "办税厅A@1",
                "特色小镇概念/企业": "企业A@4",
                "特色小镇概念/小镇管理委员会": "管委会A@0"
            },
            "tokens": [
                {
                    "BPMN_node": "税收征缴",
                    "data": {
                        "start_step": 137
                    },
                    "has_gen_next": false,
                    "id": "1618825448.349473_28286592",
                    "is_executed": false,
                    "is_fail": false,
                    "now_duration": 1
                }
            ]
        },
        {
            "role": {
                "特色小镇概念/24小时自助办税服务厅": "办税厅A@4",
                "特色小镇概念/企业": "企业A@3",
                "特色小镇概念/小镇管理委员会": "管委会A@2"
            },
            "tokens": [
                {
                    "BPMN_node": "税收征缴",
                    "data": {
                        "start_step": 137
                    },
                    "has_gen_next": false,
                    "id": "1618825448.3474224_28286579",
                    "is_executed": false,
                    "is_fail": false,
                    "now_duration": 1
                }
            ]
        },
        {
            "role": {
                "特色小镇概念/24小时自助办税服务厅": "办税厅A@4",
                "特色小镇概念/企业": "企业A@3",
                "特色小镇概念/小镇管理委员会": "管委会A@0"
            },
            "tokens": [
                {
                    "BPMN_node": "纳税身份核实",
                    "data": {
                        "start_step": 138
                    },
                    "has_gen_next": false,
                    "id": "1618825448.347962_28286583",
                    "is_executed": false,
                    "is_fail": false,
                    "now_duration": 1
                }
            ]
        },
        {
            "role": {
                "特色小镇概念/24小时自助办税服务厅": "办税厅A@1",
                "特色小镇概念/企业": "企业A@4",
                "特色小镇概念/小镇管理委员会": "管委会A@0"
            },
            "tokens": [
                {
                    "BPMN_node": "企业注册",
                    "data": {
                        "start_step": 140
                    },
                    "has_gen_next": false,
                    "id": "1618825448.350548_28286598",
                    "is_executed": false,
                    "is_fail": false,
                    "now_duration": 1
                }
            ]
        },
        {
            "role": {
                "特色小镇概念/24小时自助办税服务厅": "办税厅A@2",
                "特色小镇概念/企业": "企业A@1",
                "特色小镇概念/小镇管理委员会": "管委会A@3"
            },
            "tokens": [
                {
                    "BPMN_node": "BPMN概念/EndEvent-1",
                    "data": {
                        "start_step": 135
                    },
                    "has_gen_next": false,
                    "id": "1618825448.3488088_28286588",
                    "is_executed": false,
                    "is_fail": false,
                    "now_duration": 1
                }
            ]
        },
        {
            "role": {
                "特色小镇概念/24小时自助办税服务厅": "办税厅A@2",
                "特色小镇概念/企业": "企业A@1",
                "特色小镇概念/小镇管理委员会": "管委会A@4"
            },
            "tokens": [
                {
                    "BPMN_node": "纳税身份核实",
                    "data": {
                        "start_step": 138
                    },
                    "has_gen_next": false,
                    "id": "1618825448.3498046_28286595",
                    "is_executed": false,
                    "is_fail": false,
                    "now_duration": 1
                }
            ]
        },
        {
            "role": {
                "特色小镇概念/24小时自助办税服务厅": "办税厅A@4",
                "特色小镇概念/企业": "企业A@0",
                "特色小镇概念/小镇管理委员会": "管委会A@2"
            },
            "tokens": [
                {
                    "BPMN_node": "纳税成功",
                    "data": {
                        "start_step": 136
                    },
                    "has_gen_next": false,
                    "id": "1618825448.3468487_28286574",
                    "is_executed": false,
                    "is_fail": false,
                    "now_duration": 1
                }
            ]
        },
        {
            "role": {
                "特色小镇概念/24小时自助办税服务厅": "办税厅A@0",
                "特色小镇概念/企业": "企业A@1",
                "特色小镇概念/小镇管理委员会": "管委会A@2"
            },
            "tokens": [
                {
                    "BPMN_node": "税收征缴",
                    "data": {
                        "start_step": 137
                    },
                    "has_gen_next": false,
                    "id": "1618825448.349302_28286591",
                    "is_executed": false,
                    "is_fail": false,
                    "now_duration": 1
                }
            ]
        },
        {
            "role": {
                "特色小镇概念/24小时自助办税服务厅": "办税厅A@4",
                "特色小镇概念/企业": "企业A@2",
                "特色小镇概念/小镇管理委员会": "管委会A@1"
            },
            "tokens": [
                {
                    "BPMN_node": "企业注册",
                    "data": {
                        "start_step": 140
                    },
                    "has_gen_next": false,
                    "id": "1618825448.3469334_28286575",
                    "is_executed": false,
                    "is_fail": false,
                    "now_duration": 1
                }
            ]
        },
        {
            "role": {
                "特色小镇概念/24小时自助办税服务厅": "办税厅A@2",
                "特色小镇概念/企业": "企业A@2",
                "特色小镇概念/小镇管理委员会": "管委会A@3"
            },
            "tokens": [
                {
                    "BPMN_node": "办税厅出入口人脸识别",
                    "data": {
                        "start_step": 139
                    },
                    "has_gen_next": false,
                    "id": "1618825448.3473418_28286578",
                    "is_executed": false,
                    "is_fail": false,
                    "now_duration": 1
                }
            ]
        },
        {
            "role": {
                "特色小镇概念/24小时自助办税服务厅": "办税厅A@4",
                "特色小镇概念/企业": "企业A@1",
                "特色小镇概念/小镇管理委员会": "管委会A@0"
            },
            "tokens": [
                {
                    "BPMN_node": "办税厅出入口人脸识别",
                    "data": {
                        "start_step": 139
                    },
                    "has_gen_next": false,
                    "id": "1618825448.3466742_28286572",
                    "is_executed": false,
                    "is_fail": false,
                    "now_duration": 1
                }
            ]
        },
        {
            "role": {
                "特色小镇概念/24小时自助办税服务厅": "办税厅A@2",
                "特色小镇概念/企业": "企业A@2",
                "特色小镇概念/小镇管理委员会": "管委会A@0"
            },
            "tokens": [
                {
                    "BPMN_node": "BPMN概念/EndEvent-1",
                    "data": {
                        "start_step": 135
                    },
                    "has_gen_next": false,
                    "id": "1618825448.346766_28286573",
                    "is_executed": false,
                    "is_fail": false,
                    "now_duration": 1
                }
            ]
        },
        {
            "role": {
                "特色小镇概念/24小时自助办税服务厅": "办税厅A@3",
                "特色小镇概念/企业": "企业A@2",
                "特色小镇概念/小镇管理委员会": "管委会A@1"
            },
            "tokens": [
                {
                    "BPMN_node": "纳税身份核实",
                    "data": {
                        "start_step": 138
                    },
                    "has_gen_next": false,
                    "id": "1618825448.3503304_28286597",
                    "is_executed": false,
                    "is_fail": false,
                    "now_duration": 1
                }
            ]
        },
        {
            "role": {
                "特色小镇概念/24小时自助办税服务厅": "办税厅A@0",
                "特色小镇概念/企业": "企业A@3",
                "特色小镇概念/小镇管理委员会": "管委会A@3"
            },
            "tokens": [
                {
                    "BPMN_node": "企业注册",
                    "data": {
                        "start_step": 140
                    },
                    "has_gen_next": false,
                    "id": "1618825448.3476138_28286580",
                    "is_executed": false,
                    "is_fail": false,
                    "now_duration": 1
                }
            ]
        }
    ],
    "quota": {
        "Process平均运行时间": {
            "name": "Process平均运行时间",
            "text": "0",
            "type": "value",
            "val": 6.0
        }
    },
    "step_count": 140
}